etraxx.py
etraxx_playground-0.3.2.dist-info/METADATA
etraxx_playground-0.3.2.dist-info/WHEEL
etraxx_playground-0.3.2.dist-info/top_level.txt
etraxx_playground-0.3.2.dist-info/RECORD
