Metadata-Version: 2.4
Name: etraxx-playground
Version: 0.3.2
Summary: Just a simple Playground File for playing around :-D
Requires-Python: >=3.12
